{
  "kind": "collectionType",
  "collectionName": "postulacions",
  "info": {
    "singularName": "postulacion",
    "pluralName": "postulacions",
    "displayName": "Postulacion",
    "description": ""
  },
  "options": {
    "draftAndPublish": true
  },
  "pluginOptions": {},
  "attributes": {
    "representante": {
      "type": "string"
    },
    "correo": {
      "type": "email"
    },
    "cuenta": {
      "type": "string"
    },
    "celular": {
      "type": "string"
    },
    "genero": {
      "type": "enumeration",
      "enum": [
        "Masculino",
        "Femenino",
        "Otro"
      ]
    },
    "descripcion": {
      "type": "text"
    },
    "redesSociales": {
      "type": "boolean"
    },
    "equipoTrabajo": {
      "type": "boolean"
    },
    "expectativas": {
      "type": "text"
    },
    "tipo": {
      "type": "enumeration",
      "enum": [
        "Idea",
        "Emprendimiento"
      ]
    },
    "rubro": {
      "type": "enumeration",
      "enum": [
        "Comercial",
        "Social",
        "Emprendimiento tecnológico",
        "healt_care",
        "Artesanal"
      ]
    },
    "sede": {
      "type": "enumeration",
      "enum": [
        "San Pedro Sula",
        "Tegucigalpa",
        "La Ceiba"
      ]
    },
    "estado": {
      "type": "string"
    }
  }
}
